{
	"addw":"0",
	"expanded":"1",
	"extends":
	[
		{
			"addw":"0",
			"compid":"44",
			"compname":"gate",
			"expanded":"1",
			"posx":"914",
			"posy":"707",
			"ui":
			[
				{
					"addw":"141",
					"compid":"36",
					"compname":"xywh",
					"compvalues":
					[
						[
							"50",
							"150 + aV * 120",
							"300",
							"100"
						]
					],
					"expanded":"1",
					"posx":"1280",
					"posy":"746",
					"ui":
					[
						{
							"addw":"0",
							"compid":"37",
							"compname":"color",
							"compvalues":
							[
								[
									"255",
									"128",
									"255",
									"128"
								]
							],
							"expanded":"1",
							"posx":"1836",
							"posy":"743",
							"ui":
							[
								{
									"addw":"0",
									"compid":"38",
									"compname":"fill",
									"expanded":"1",
									"posx":"2178",
									"posy":"756"
								}
							]
						},
						{
							"addw":"0",
							"compid":"39",
							"compname":"color",
							"compvalues":
							[
								[
									"0",
									"0",
									"0"
								]
							],
							"expanded":"1",
							"posx":"1839",
							"posy":"913",
							"ui":
							[
								{
									"addw":"36",
									"compid":"40",
									"compname":"font",
									"compvalues":
									[
										[
											"2.5",
											"d.data.fonts.0.name"
										]
									],
									"expanded":"1",
									"posx":"2182",
									"posy":"912",
									"ui":
									[
										{
											"addw":"112",
											"compid":"41",
											"compname":"text",
											"compvalues":
											[
												[
													"'no'@'d.data.kiosk.menu.'+ aV"
												]
											],
											"expanded":"1",
											"posx":"2557",
											"posy":"910"
										}
									]
								}
							]
						}
					]
				}
			],
			"uiname":"menu"
		}
	],
	"posx":"-398",
	"posy":"-39",
	"ui":
	[
		{
			"addw":"0",
			"compid":"22",
			"compname":"fill",
			"expanded":"1",
			"posx":"55",
			"posy":"-54"
		},
		{
			"addw":"0",
			"compid":"30",
			"compname":"ltrb",
			"compvalues":
			[
				[
					"20",
					"20",
					"pW-20",
					"100"
				]
			],
			"expanded":"1",
			"posx":"53",
			"posy":"53",
			"ui":
			[
				{
					"addw":"0",
					"compid":"31",
					"compname":"color",
					"compvalues":
					[
						[
							"255",
							"255",
							"128"
						]
					],
					"expanded":"1",
					"posx":"381",
					"posy":"67",
					"ui":
					[
						{
							"addw":"0",
							"compid":"32",
							"compname":"fill",
							"expanded":"1",
							"posx":"723",
							"posy":"81"
						}
					]
				},
				{
					"addw":"0",
					"compid":"33",
					"compname":"color",
					"compvalues":
					[
						[
							"0",
							"0",
							"0"
						]
					],
					"expanded":"1",
					"posx":"385",
					"posy":"231",
					"ui":
					[
						{
							"addw":"36",
							"compid":"35",
							"compname":"font",
							"compvalues":
							[
								[
									"2.5",
									"d.data.fonts.0.name"
								]
							],
							"expanded":"1",
							"posx":"728",
							"posy":"230",
							"ui":
							[
								{
									"addw":"0",
									"compid":"34",
									"compname":"text",
									"compvalues":
									[
										[
											"d.data.kiosk.name"
										]
									],
									"expanded":"1",
									"posx":"1103",
									"posy":"228"
								}
							]
						}
					]
				}
			]
		},
		{
			"addw":"87",
			"compid":"42",
			"compname":"loop",
			"expanded":"1",
			"posx":"57",
			"posy":"542",
			"ui":
			[
				{
					"addw":"0",
					"compid":"43",
					"compname":"jump",
					"expanded":"1",
					"posx":"491",
					"posy":"598",
					"uiname":"menu"
				}
			],
			"uiloop":"5",
			"uiname":"a"
		}
	]
}
